[{"featureShape":[2048],"annotation":"african_elephant"},{"featureShape":[2048],"annotation":"african_elephant"},{"featureShape":[2048],"annotation":"african_elephant"},{"featureShape":[2048],"annotation":"african_elephant"},{"featureShape":[2048],"annotation":"african_elephant"},{"featureShape":[2048],"annotation":"african_elephant"},{"featureShape":[2048],"annotation":"african_elephant"},{"featureShape":[2048],"annotation":"african_elephant"},{"featureShape":[2048],"annotation":"african_elephant"},{"featureShape":[2048],"annotation":"african_elephant"},{"featureShape":[2048],"annotation":"african_elephant"},{"annotation":"african_elephant","featureShape":[2048]},{"annotation":"african_elephant","featureShape":[2048]},{"annotation":"african_elephant","featureShape":[2048]},{"featureShape":[2048],"annotation":"african_elephant"},{"annotation":"african_elephant","featureShape":[2048]},{"featureShape":[2048],"annotation":"african_elephant"},{"featureShape":[2048],"annotation":"african_elephant"},{"annotation":"african_elephant","featureShape":[2048]},{"featureShape":[2048],"annotation":"african_elephant"},{"annotation":"african_elephant","featureShape":[2048]},{"annotation":"african_elephant","featureShape":[2048]},{"annotation":"african_elephant","featureShape":[2048]},{"featureShape":[2048],"annotation":"african_elephant"},{"featureShape":[2048],"annotation":"african_elephant"},{"featureShape":[2048],"annotation":"african_elephant"},{"featureShape":[2048],"annotation":"african_elephant"},{"featureShape":[2048],"annotation":"african_elephant"},{"featureShape":[2048],"annotation":"african_elephant"},{"featureShape":[2048],"annotation":"african_elephant"},{"featureShape":[2048],"annotation":"african_elephant"},{"featureShape":[2048],"annotation":"african_elephant"},{"featureShape":[2048],"annotation":"african_elephant"},{"annotation":"african_elephant","featureShape":[2048]},{"featureShape":[2048],"annotation":"african_elephant"},{"featureShape":[2048],"annotation":"african_elephant"},{"annotation":"african_elephant","featureShape":[2048]},{"featureShape":[2048],"annotation":"african_elephant"},{"featureShape":[2048],"annotation":"african_elephant"},{"annotation":"african_elephant","featureShape":[2048]},{"featureShape":[2048],"annotation":"african_elephant"},{"annotation":"african_elephant","featureShape":[2048]},{"featureShape":[2048],"annotation":"african_elephant"},{"annotation":"african_elephant","featureShape":[2048]},{"annotation":"african_elephant","featureShape":[2048]},{"annotation":"african_elephant","featureShape":[2048]},{"featureShape":[2048],"annotation":"african_elephant"},{"annotation":"african_elephant","featureShape":[2048]},{"featureShape":[2048],"annotation":"african_elephant"},{"featureShape":[2048],"annotation":"african_elephant"},{"featureShape":[2048],"annotation":"african_elephant"},{"annotation":"african_elephant","featureShape":[2048]},{"annotation":"african_elephant","featureShape":[2048]},{"annotation":"african_elephant","featureShape":[2048]},{"featureShape":[2048],"annotation":"african_elephant"},{"annotation":"african_elephant","featureShape":[2048]},{"annotation":"african_elephant","featureShape":[2048]},{"annotation":"african_elephant","featureShape":[2048]},{"featureShape":[2048],"annotation":"african_elephant"},{"annotation":"african_elephant","featureShape":[2048]},{"featureShape":[2048],"annotation":"african_elephant"},{"featureShape":[2048],"annotation":"african_elephant"},{"featureShape":[2048],"annotation":"african_elephant"},{"annotation":"african_elephant","featureShape":[2048]},{"featureShape":[2048],"annotation":"african_elephant"},{"annotation":"african_elephant","featureShape":[2048]},{"annotation":"african_elephant","featureShape":[2048]},{"annotation":"african_elephant","featureShape":[2048]},{"annotation":"african_elephant","featureShape":[2048]},{"featureShape":[2048],"annotation":"african_elephant"},{"featureShape":[2048],"annotation":"african_elephant"},{"featureShape":[2048],"annotation":"african_elephant"},{"featureShape":[2048],"annotation":"african_elephant"},{"annotation":"african_elephant","featureShape":[2048]},{"annotation":"african_elephant","featureShape":[2048]},{"featureShape":[2048],"annotation":"african_elephant"},{"annotation":"african_elephant","featureShape":[2048]},{"annotation":"african_elephant","featureShape":[2048]},{"featureShape":[2048],"annotation":"african_elephant"},{"annotation":"african_elephant","featureShape":[2048]},{"annotation":"african_elephant","featureShape":[2048]},{"featureShape":[2048],"annotation":"african_elephant"},{"annotation":"african_elephant","featureShape":[2048]},{"featureShape":[2048],"annotation":"african_elephant"},{"featureShape":[2048],"annotation":"african_elephant"},{"annotation":"african_elephant","featureShape":[2048]},{"featureShape":[2048],"annotation":"african_elephant"},{"annotation":"african_elephant","featureShape":[2048]},{"annotation":"african_elephant","featureShape":[2048]},{"featureShape":[2048],"annotation":"african_elephant"},{"annotation":"african_elephant","featureShape":[2048]},{"annotation":"african_elephant","featureShape":[2048]},{"featureShape":[2048],"annotation":"african_elephant"},{"featureShape":[2048],"annotation":"african_elephant"},{"annotation":"african_elephant","featureShape":[2048]},{"featureShape":[2048],"annotation":"african_elephant"},{"annotation":"african_elephant","featureShape":[2048]},{"annotation":"african_elephant","featureShape":[2048]},{"featureShape":[2048],"annotation":"african_elephant"},{"featureShape":[2048],"annotation":"african_elephant"},{"annotation":"african_elephant","featureShape":[2048]},{"annotation":"african_elephant","featureShape":[2048]},{"featureShape":[2048],"annotation":"african_elephant"},{"featureShape":[2048],"annotation":"african_elephant"},{"annotation":"african_elephant","featureShape":[2048]},{"annotation":"african_elephant","featureShape":[2048]},{"featureShape":[2048],"annotation":"african_elephant"},{"featureShape":[2048],"annotation":"african_elephant"},{"annotation":"african_elephant","featureShape":[2048]},{"featureShape":[2048],"annotation":"african_elephant"},{"featureShape":[2048],"annotation":"african_elephant"},{"annotation":"african_elephant","featureShape":[2048]},{"featureShape":[2048],"annotation":"african_elephant"},{"featureShape":[2048],"annotation":"african_elephant"},{"featureShape":[2048],"annotation":"african_elephant"},{"featureShape":[2048],"annotation":"african_elephant"},{"featureShape":[2048],"annotation":"african_elephant"},{"annotation":"african_elephant","featureShape":[2048]},{"featureShape":[2048],"annotation":"african_elephant"},{"annotation":"african_elephant","featureShape":[2048]},{"featureShape":[2048],"annotation":"african_elephant"},{"featureShape":[2048],"annotation":"african_elephant"},{"featureShape":[2048],"annotation":"african_elephant"},{"annotation":"african_elephant","featureShape":[2048]},{"annotation":"african_elephant","featureShape":[2048]},{"featureShape":[2048],"annotation":"african_elephant"},{"annotation":"african_elephant","featureShape":[2048]},{"featureShape":[2048],"annotation":"african_elephant"},{"annotation":"african_elephant","featureShape":[2048]},{"featureShape":[2048],"annotation":"african_elephant"},{"featureShape":[2048],"annotation":"african_elephant"},{"featureShape":[2048],"annotation":"african_elephant"},{"annotation":"african_elephant","featureShape":[2048]},{"featureShape":[2048],"annotation":"african_elephant"},{"annotation":"african_elephant","featureShape":[2048]},{"featureShape":[2048],"annotation":"african_elephant"},{"featureShape":[2048],"annotation":"african_elephant"},{"annotation":"african_elephant","featureShape":[2048]},{"annotation":"african_elephant","featureShape":[2048]},{"annotation":"african_elephant","featureShape":[2048]},{"annotation":"african_elephant","featureShape":[2048]},{"featureShape":[2048],"annotation":"african_elephant"},{"featureShape":[2048],"annotation":"african_elephant"},{"featureShape":[2048],"annotation":"african_elephant"},{"featureShape":[2048],"annotation":"african_elephant"},{"featureShape":[2048],"annotation":"african_elephant"},{"featureShape":[2048],"annotation":"african_elephant"},{"annotation":"african_elephant","featureShape":[2048]},{"featureShape":[2048],"annotation":"african_elephant"},{"annotation":"african_elephant","featureShape":[2048]},{"featureShape":[2048],"annotation":"african_elephant"},{"annotation":"african_elephant","featureShape":[2048]},{"featureShape":[2048],"annotation":"african_elephant"},{"featureShape":[2048],"annotation":"african_elephant"},{"featureShape":[2048],"annotation":"african_elephant"},{"featureShape":[2048],"annotation":"african_elephant"},{"featureShape":[2048],"annotation":"african_elephant"},{"featureShape":[2048],"annotation":"african_elephant"},{"featureShape":[2048],"annotation":"african_elephant"},{"featureShape":[2048],"annotation":"african_elephant"},{"featureShape":[2048],"annotation":"african_elephant"},{"annotation":"african_elephant","featureShape":[2048]},{"annotation":"african_elephant","featureShape":[2048]},{"featureShape":[2048],"annotation":"african_elephant"},{"featureShape":[2048],"annotation":"african_elephant"},{"featureShape":[2048],"annotation":"african_elephant"},{"annotation":"african_elephant","featureShape":[2048]},{"annotation":"african_elephant","featureShape":[2048]},{"featureShape":[2048],"annotation":"african_elephant"},{"featureShape":[2048],"annotation":"african_elephant"},{"featureShape":[2048],"annotation":"african_elephant"},{"featureShape":[2048],"annotation":"african_elephant"},{"annotation":"african_elephant","featureShape":[2048]},{"annotation":"african_elephant","featureShape":[2048]},{"featureShape":[2048],"annotation":"african_elephant"},{"featureShape":[2048],"annotation":"african_elephant"},{"annotation":"african_elephant","featureShape":[2048]},{"featureShape":[2048],"annotation":"african_elephant"},{"annotation":"african_elephant","featureShape":[2048]},{"featureShape":[2048],"annotation":"african_elephant"},{"featureShape":[2048],"annotation":"african_elephant"},{"featureShape":[2048],"annotation":"african_elephant"},{"featureShape":[2048],"annotation":"african_elephant"},{"annotation":"african_elephant","featureShape":[2048]},{"featureShape":[2048],"annotation":"african_elephant"},{"annotation":"african_elephant","featureShape":[2048]},{"featureShape":[2048],"annotation":"african_elephant"},{"featureShape":[2048],"annotation":"african_elephant"},{"featureShape":[2048],"annotation":"african_elephant"},{"annotation":"african_elephant","featureShape":[2048]},{"featureShape":[2048],"annotation":"african_elephant"},{"annotation":"african_elephant","featureShape":[2048]},{"featureShape":[2048],"annotation":"african_elephant"},{"annotation":"african_elephant","featureShape":[2048]},{"featureShape":[2048],"annotation":"african_elephant"},{"featureShape":[2048],"annotation":"african_elephant"},{"annotation":"african_elephant","featureShape":[2048]},{"featureShape":[2048],"annotation":"african_elephant"},{"annotation":"african_elephant","featureShape":[2048]},{"annotation":"african_elephant","featureShape":[2048]},{"featureShape":[2048],"annotation":"african_elephant"},{"featureShape":[2048],"annotation":"african_elephant"},{"featureShape":[2048],"annotation":"african_elephant"},{"annotation":"african_elephant","featureShape":[2048]},{"annotation":"african_elephant","featureShape":[2048]},{"featureShape":[2048],"annotation":"african_elephant"},{"annotation":"african_elephant","featureShape":[2048]},{"featureShape":[2048],"annotation":"african_elephant"},{"featureShape":[2048],"annotation":"african_elephant"},{"annotation":"african_elephant","featureShape":[2048]},{"annotation":"african_elephant","featureShape":[2048]},{"annotation":"african_elephant","featureShape":[2048]},{"annotation":"african_elephant","featureShape":[2048]},{"annotation":"african_elephant","featureShape":[2048]},{"annotation":"african_elephant","featureShape":[2048]},{"featureShape":[2048],"annotation":"african_elephant"},{"annotation":"african_elephant","featureShape":[2048]},{"annotation":"african_elephant","featureShape":[2048]},{"annotation":"african_elephant","featureShape":[2048]},{"featureShape":[2048],"annotation":"african_elephant"},{"annotation":"african_elephant","featureShape":[2048]},{"annotation":"african_elephant","featureShape":[2048]},{"annotation":"african_elephant","featureShape":[2048]},{"annotation":"african_elephant","featureShape":[2048]},{"featureShape":[2048],"annotation":"african_elephant"},{"annotation":"african_elephant","featureShape":[2048]},{"featureShape":[2048],"annotation":"african_elephant"},{"featureShape":[2048],"annotation":"african_elephant"},{"featureShape":[2048],"annotation":"african_elephant"},{"annotation":"african_elephant","featureShape":[2048]},{"annotation":"african_elephant","featureShape":[2048]},{"featureShape":[2048],"annotation":"african_elephant"},{"featureShape":[2048],"annotation":"african_elephant"},{"featureShape":[2048],"annotation":"african_elephant"},{"featureShape":[2048],"annotation":"african_elephant"},{"featureShape":[2048],"annotation":"african_elephant"},{"featureShape":[2048],"annotation":"african_elephant"},{"annotation":"african_elephant","featureShape":[2048]},{"featureShape":[2048],"annotation":"african_elephant"},{"featureShape":[2048],"annotation":"african_elephant"},{"featureShape":[2048],"annotation":"african_elephant"},{"annotation":"african_elephant","featureShape":[2048]},{"annotation":"african_elephant","featureShape":[2048]},{"featureShape":[2048],"annotation":"african_elephant"},{"featureShape":[2048],"annotation":"african_elephant"},{"featureShape":[2048],"annotation":"african_elephant"},{"annotation":"african_elephant","featureShape":[2048]},{"featureShape":[2048],"annotation":"african_elephant"},{"featureShape":[2048],"annotation":"african_elephant"},{"featureShape":[2048],"annotation":"african_elephant"},{"annotation":"african_elephant","featureShape":[2048]},{"annotation":"african_elephant","featureShape":[2048]},{"annotation":"african_elephant","featureShape":[2048]},{"annotation":"african_elephant","featureShape":[2048]},{"featureShape":[2048],"annotation":"african_elephant"},{"annotation":"african_elephant","featureShape":[2048]},{"featureShape":[2048],"annotation":"african_elephant"},{"featureShape":[2048],"annotation":"african_elephant"},{"annotation":"african_elephant","featureShape":[2048]},{"annotation":"african_elephant","featureShape":[2048]},{"featureShape":[2048],"annotation":"african_elephant"},{"featureShape":[2048],"annotation":"african_elephant"},{"featureShape":[2048],"annotation":"african_elephant"},{"annotation":"african_elephant","featureShape":[2048]},{"featureShape":[2048],"annotation":"african_elephant"},{"featureShape":[2048],"annotation":"african_elephant"},{"featureShape":[2048],"annotation":"african_elephant"},{"featureShape":[2048],"annotation":"african_elephant"},{"annotation":"african_elephant","featureShape":[2048]},{"annotation":"african_elephant","featureShape":[2048]},{"annotation":"african_elephant","featureShape":[2048]},{"featureShape":[2048],"annotation":"african_elephant"},{"annotation":"african_elephant","featureShape":[2048]},{"featureShape":[2048],"annotation":"african_elephant"},{"annotation":"african_elephant","featureShape":[2048]},{"featureShape":[2048],"annotation":"african_elephant"},{"featureShape":[2048],"annotation":"african_elephant"},{"annotation":"african_elephant","featureShape":[2048]},{"featureShape":[2048],"annotation":"african_elephant"},{"annotation":"african_elephant","featureShape":[2048]},{"featureShape":[2048],"annotation":"african_elephant"},{"featureShape":[2048],"annotation":"african_elephant"},{"annotation":"african_elephant","featureShape":[2048]},{"featureShape":[2048],"annotation":"african_elephant"},{"featureShape":[2048],"annotation":"african_elephant"},{"featureShape":[2048],"annotation":"african_elephant"},{"featureShape":[2048],"annotation":"african_elephant"},{"featureShape":[2048],"annotation":"african_elephant"},{"annotation":"african_elephant","featureShape":[2048]},{"annotation":"african_elephant","featureShape":[2048]},{"featureShape":[2048],"annotation":"african_elephant"},{"annotation":"african_elephant","featureShape":[2048]},{"annotation":"african_elephant","featureShape":[2048]},{"featureShape":[2048],"annotation":"african_elephant"},{"featureShape":[2048],"annotation":"african_elephant"},{"featureShape":[2048],"annotation":"african_elephant"},{"annotation":"african_elephant","featureShape":[2048]},{"featureShape":[2048],"annotation":"african_elephant"},{"featureShape":[2048],"annotation":"african_elephant"},{"featureShape":[2048],"annotation":"african_elephant"},{"featureShape":[2048],"annotation":"african_elephant"},{"annotation":"african_elephant","featureShape":[2048]},{"featureShape":[2048],"annotation":"african_elephant"},{"annotation":"african_elephant","featureShape":[2048]},{"featureShape":[2048],"annotation":"african_elephant"},{"featureShape":[2048],"annotation":"african_elephant"},{"featureShape":[2048],"annotation":"african_elephant"},{"featureShape":[2048],"annotation":"african_elephant"},{"featureShape":[2048],"annotation":"african_elephant"},{"annotation":"african_elephant","featureShape":[2048]},{"featureShape":[2048],"annotation":"african_elephant"},{"annotation":"african_elephant","featureShape":[2048]},{"featureShape":[2048],"annotation":"african_elephant"},{"annotation":"african_elephant","featureShape":[2048]},{"featureShape":[2048],"annotation":"african_elephant"},{"annotation":"african_elephant","featureShape":[2048]},{"featureShape":[2048],"annotation":"african_elephant"},{"featureShape":[2048],"annotation":"african_elephant"},{"featureShape":[2048],"annotation":"african_elephant"},{"annotation":"african_elephant","featureShape":[2048]},{"featureShape":[2048],"annotation":"african_elephant"},{"annotation":"african_elephant","featureShape":[2048]},{"annotation":"african_elephant","featureShape":[2048]},{"featureShape":[2048],"annotation":"african_elephant"},{"annotation":"african_elephant","featureShape":[2048]},{"featureShape":[2048],"annotation":"african_elephant"},{"featureShape":[2048],"annotation":"african_elephant"},{"annotation":"african_elephant","featureShape":[2048]},{"annotation":"african_elephant","featureShape":[2048]},{"featureShape":[2048],"annotation":"african_elephant"},{"annotation":"african_elephant","featureShape":[2048]},{"annotation":"african_elephant","featureShape":[2048]},{"featureShape":[2048],"annotation":"african_elephant"},{"featureShape":[2048],"annotation":"african_elephant"},{"annotation":"african_elephant","featureShape":[2048]},{"featureShape":[2048],"annotation":"african_elephant"},{"annotation":"african_elephant","featureShape":[2048]},{"annotation":"african_elephant","featureShape":[2048]},{"featureShape":[2048],"annotation":"african_elephant"},{"featureShape":[2048],"annotation":"african_elephant"},{"featureShape":[2048],"annotation":"african_elephant"},{"featureShape":[2048],"annotation":"african_elephant"},{"featureShape":[2048],"annotation":"african_elephant"},{"annotation":"african_elephant","featureShape":[2048]},{"annotation":"african_elephant","featureShape":[2048]},{"featureShape":[2048],"annotation":"african_elephant"},{"featureShape":[2048],"annotation":"african_elephant"},{"featureShape":[2048],"annotation":"african_elephant"},{"featureShape":[2048],"annotation":"african_elephant"},{"annotation":"african_elephant","featureShape":[2048]},{"featureShape":[2048],"annotation":"african_elephant"},{"featureShape":[2048],"annotation":"african_elephant"},{"featureShape":[2048],"annotation":"african_elephant"},{"featureShape":[2048],"annotation":"african_elephant"},{"featureShape":[2048],"annotation":"african_elephant"},{"featureShape":[2048],"annotation":"african_elephant"},{"featureShape":[2048],"annotation":"african_elephant"},{"annotation":"african_elephant","featureShape":[2048]},{"featureShape":[2048],"annotation":"african_elephant"},{"annotation":"african_elephant","featureShape":[2048]},{"annotation":"african_elephant","featureShape":[2048]},{"featureShape":[2048],"annotation":"african_elephant"},{"featureShape":[2048],"annotation":"african_elephant"},{"featureShape":[2048],"annotation":"african_elephant"},{"featureShape":[2048],"annotation":"african_elephant"},{"annotation":"african_elephant","featureShape":[2048]},{"featureShape":[2048],"annotation":"african_elephant"},{"featureShape":[2048],"annotation":"african_elephant"},{"annotation":"african_elephant","featureShape":[2048]},{"featureShape":[2048],"annotation":"african_elephant"},{"annotation":"african_elephant","featureShape":[2048]},{"annotation":"african_elephant","featureShape":[2048]},{"annotation":"african_elephant","featureShape":[2048]},{"featureShape":[2048],"annotation":"african_elephant"},{"featureShape":[2048],"annotation":"african_elephant"},{"annotation":"african_elephant","featureShape":[2048]},{"featureShape":[2048],"annotation":"african_elephant"},{"annotation":"african_elephant","featureShape":[2048]},{"featureShape":[2048],"annotation":"african_elephant"},{"featureShape":[2048],"annotation":"african_elephant"},{"featureShape":[2048],"annotation":"african_elephant"},{"annotation":"african_elephant","featureShape":[2048]},{"featureShape":[2048],"annotation":"african_elephant"},{"annotation":"african_elephant","featureShape":[2048]},{"annotation":"african_elephant","featureShape":[2048]},{"featureShape":[2048],"annotation":"african_elephant"},{"featureShape":[2048],"annotation":"african_elephant"},{"featureShape":[2048],"annotation":"african_elephant"},{"featureShape":[2048],"annotation":"african_elephant"},{"annotation":"african_elephant","featureShape":[2048]},{"annotation":"african_elephant","featureShape":[2048]},{"featureShape":[2048],"annotation":"african_elephant"},{"annotation":"african_elephant","featureShape":[2048]},{"annotation":"african_elephant","featureShape":[2048]},{"annotation":"african_elephant","featureShape":[2048]},{"annotation":"african_elephant","featureShape":[2048]},{"featureShape":[2048],"annotation":"african_elephant"},{"featureShape":[2048],"annotation":"african_elephant"},{"annotation":"african_elephant","featureShape":[2048]},{"annotation":"african_elephant","featureShape":[2048]},{"annotation":"african_elephant","featureShape":[2048]},{"annotation":"african_elephant","featureShape":[2048]},{"featureShape":[2048],"annotation":"african_elephant"},{"featureShape":[2048],"annotation":"african_elephant"},{"annotation":"african_elephant","featureShape":[2048]},{"annotation":"african_elephant","featureShape":[2048]},{"featureShape":[2048],"annotation":"african_elephant"},{"annotation":"african_elephant","featureShape":[2048]},{"featureShape":[2048],"annotation":"african_elephant"},{"annotation":"african_elephant","featureShape":[2048]},{"featureShape":[2048],"annotation":"african_elephant"},{"featureShape":[2048],"annotation":"african_elephant"},{"annotation":"african_elephant","featureShape":[2048]},{"featureShape":[2048],"annotation":"african_elephant"},{"featureShape":[2048],"annotation":"african_elephant"},{"featureShape":[2048],"annotation":"african_elephant"},{"featureShape":[2048],"annotation":"african_elephant"},{"featureShape":[2048],"annotation":"african_elephant"},{"featureShape":[2048],"annotation":"african_elephant"},{"featureShape":[2048],"annotation":"african_elephant"},{"featureShape":[2048],"annotation":"african_elephant"},{"annotation":"african_elephant","featureShape":[2048]},{"featureShape":[2048],"annotation":"african_elephant"},{"annotation":"african_elephant","featureShape":[2048]},{"annotation":"african_elephant","featureShape":[2048]},{"annotation":"african_elephant","featureShape":[2048]},{"featureShape":[2048],"annotation":"african_elephant"},{"annotation":"african_elephant","featureShape":[2048]},{"featureShape":[2048],"annotation":"african_elephant"},{"featureShape":[2048],"annotation":"african_elephant"},{"featureShape":[2048],"annotation":"african_elephant"},{"featureShape":[2048],"annotation":"african_elephant"},{"featureShape":[2048],"annotation":"african_elephant"},{"annotation":"african_elephant","featureShape":[2048]},{"annotation":"african_elephant","featureShape":[2048]},{"featureShape":[2048],"annotation":"african_elephant"},{"featureShape":[2048],"annotation":"african_elephant"},{"featureShape":[2048],"annotation":"african_elephant"},{"annotation":"african_elephant","featureShape":[2048]},{"featureShape":[2048],"annotation":"african_elephant"},{"annotation":"african_elephant","featureShape":[2048]},{"featureShape":[2048],"annotation":"african_elephant"},{"featureShape":[2048],"annotation":"african_elephant"},{"featureShape":[2048],"annotation":"african_elephant"},{"featureShape":[2048],"annotation":"african_elephant"},{"featureShape":[2048],"annotation":"african_elephant"},{"featureShape":[2048],"annotation":"african_elephant"},{"annotation":"african_elephant","featureShape":[2048]},{"featureShape":[2048],"annotation":"african_elephant"},{"annotation":"african_elephant","featureShape":[2048]},{"annotation":"african_elephant","featureShape":[2048]},{"annotation":"african_elephant","featureShape":[2048]},{"featureShape":[2048],"annotation":"african_elephant"},{"featureShape":[2048],"annotation":"african_elephant"},{"featureShape":[2048],"annotation":"african_elephant"},{"featureShape":[2048],"annotation":"african_elephant"},{"featureShape":[2048],"annotation":"african_elephant"},{"featureShape":[2048],"annotation":"african_elephant"},{"featureShape":[2048],"annotation":"african_elephant"},{"annotation":"african_elephant","featureShape":[2048]},{"featureShape":[2048],"annotation":"african_elephant"},{"featureShape":[2048],"annotation":"african_elephant"},{"annotation":"african_elephant","featureShape":[2048]},{"annotation":"african_elephant","featureShape":[2048]},{"annotation":"african_elephant","featureShape":[2048]},{"featureShape":[2048],"annotation":"african_elephant"},{"annotation":"african_elephant","featureShape":[2048]},{"annotation":"african_elephant","featureShape":[2048]},{"featureShape":[2048],"annotation":"african_elephant"},{"annotation":"african_elephant","featureShape":[2048]},{"annotation":"african_elephant","featureShape":[2048]},{"featureShape":[2048],"annotation":"african_elephant"},{"annotation":"african_elephant","featureShape":[2048]},{"annotation":"african_elephant","featureShape":[2048]},{"annotation":"african_elephant","featureShape":[2048]},{"featureShape":[2048],"annotation":"african_elephant"},{"featureShape":[2048],"annotation":"african_elephant"},{"annotation":"african_elephant","featureShape":[2048]},{"featureShape":[2048],"annotation":"african_elephant"},{"featureShape":[2048],"annotation":"african_elephant"},{"featureShape":[2048],"annotation":"african_elephant"},{"annotation":"african_elephant","featureShape":[2048]},{"annotation":"african_elephant","featureShape":[2048]},{"featureShape":[2048],"annotation":"african_elephant"},{"annotation":"african_elephant","featureShape":[2048]},{"annotation":"african_elephant","featureShape":[2048]},{"featureShape":[2048],"annotation":"african_elephant"},{"featureShape":[2048],"annotation":"african_elephant"},{"annotation":"african_elephant","featureShape":[2048]},{"annotation":"african_elephant","featureShape":[2048]},{"featureShape":[2048],"annotation":"african_elephant"},{"annotation":"african_elephant","featureShape":[2048]},{"annotation":"african_elephant","featureShape":[2048]},{"annotation":"african_elephant","featureShape":[2048]},{"featureShape":[2048],"annotation":"african_elephant"},{"annotation":"african_elephant","featureShape":[2048]},{"annotation":"african_elephant","featureShape":[2048]},{"featureShape":[2048],"annotation":"african_elephant"},{"featureShape":[2048],"annotation":"african_elephant"},{"featureShape":[2048],"annotation":"african_elephant"},{"featureShape":[2048],"annotation":"african_elephant"},{"annotation":"african_elephant","featureShape":[2048]},{"annotation":"african_elephant","featureShape":[2048]},{"featureShape":[2048],"annotation":"african_elephant"},{"annotation":"african_elephant","featureShape":[2048]},{"annotation":"african_elephant","featureShape":[2048]},{"featureShape":[2048],"annotation":"african_elephant"},{"featureShape":[2048],"annotation":"african_elephant"},{"annotation":"african_elephant","featureShape":[2048]},{"featureShape":[2048],"annotation":"african_elephant"},{"featureShape":[2048],"annotation":"african_elephant"},{"annotation":"african_elephant","featureShape":[2048]},{"annotation":"african_elephant","featureShape":[2048]},{"featureShape":[2048],"annotation":"african_elephant"},{"annotation":"african_elephant","featureShape":[2048]},{"annotation":"african_elephant","featureShape":[2048]},{"annotation":"african_elephant","featureShape":[2048]},{"featureShape":[2048],"annotation":"african_elephant"},{"annotation":"african_elephant","featureShape":[2048]},{"featureShape":[2048],"annotation":"african_elephant"},{"featureShape":[2048],"annotation":"african_elephant"},{"annotation":"african_elephant","featureShape":[2048]},{"featureShape":[2048],"annotation":"african_elephant"},{"featureShape":[2048],"annotation":"african_elephant"},{"featureShape":[2048],"annotation":"african_elephant"},{"featureShape":[2048],"annotation":"african_elephant"},{"annotation":"african_elephant","featureShape":[2048]},{"annotation":"african_elephant","featureShape":[2048]},{"featureShape":[2048],"annotation":"african_elephant"},{"annotation":"african_elephant","featureShape":[2048]},{"annotation":"african_elephant","featureShape":[2048]},{"featureShape":[2048],"annotation":"african_elephant"},{"featureShape":[2048],"annotation":"african_elephant"},{"featureShape":[2048],"annotation":"african_elephant"},{"featureShape":[2048],"annotation":"african_elephant"},{"annotation":"african_elephant","featureShape":[2048]},{"featureShape":[2048],"annotation":"african_elephant"},{"annotation":"african_elephant","featureShape":[2048]},{"annotation":"african_elephant","featureShape":[2048]},{"featureShape":[2048],"annotation":"african_elephant"},{"featureShape":[2048],"annotation":"african_elephant"},{"featureShape":[2048],"annotation":"african_elephant"},{"annotation":"african_elephant","featureShape":[2048]},{"annotation":"african_elephant","featureShape":[2048]},{"featureShape":[2048],"annotation":"african_elephant"},{"annotation":"african_elephant","featureShape":[2048]},{"featureShape":[2048],"annotation":"african_elephant"},{"featureShape":[2048],"annotation":"african_elephant"},{"annotation":"african_elephant","featureShape":[2048]},{"annotation":"african_elephant","featureShape":[2048]},{"featureShape":[2048],"annotation":"african_elephant"},{"annotation":"african_elephant","featureShape":[2048]},{"annotation":"african_elephant","featureShape":[2048]},{"featureShape":[2048],"annotation":"african_elephant"},{"annotation":"african_elephant","featureShape":[2048]},{"annotation":"african_elephant","featureShape":[2048]},{"annotation":"african_elephant","featureShape":[2048]},{"annotation":"african_elephant","featureShape":[2048]},{"annotation":"african_elephant","featureShape":[2048]},{"featureShape":[2048],"annotation":"african_elephant"},{"annotation":"african_elephant","featureShape":[2048]},{"featureShape":[2048],"annotation":"african_elephant"},{"featureShape":[2048],"annotation":"african_elephant"},{"featureShape":[2048],"annotation":"african_elephant"},{"featureShape":[2048],"annotation":"african_elephant"},{"featureShape":[2048],"annotation":"african_elephant"},{"featureShape":[2048],"annotation":"african_elephant"},{"featureShape":[2048],"annotation":"african_elephant"},{"featureShape":[2048],"annotation":"african_elephant"},{"annotation":"african_elephant","featureShape":[2048]},{"annotation":"african_elephant","featureShape":[2048]},{"featureShape":[2048],"annotation":"african_elephant"},{"featureShape":[2048],"annotation":"african_elephant"},{"annotation":"african_elephant","featureShape":[2048]},{"annotation":"african_elephant","featureShape":[2048]},{"featureShape":[2048],"annotation":"african_elephant"},{"featureShape":[2048],"annotation":"african_elephant"},{"featureShape":[2048],"annotation":"african_elephant"},{"featureShape":[2048],"annotation":"african_elephant"},{"featureShape":[2048],"annotation":"african_elephant"},{"annotation":"african_elephant","featureShape":[2048]},{"featureShape":[2048],"annotation":"african_elephant"},{"annotation":"african_elephant","featureShape":[2048]},{"annotation":"african_elephant","featureShape":[2048]},{"featureShape":[2048],"annotation":"african_elephant"},{"featureShape":[2048],"annotation":"african_elephant"},{"featureShape":[2048],"annotation":"african_elephant"},{"featureShape":[2048],"annotation":"african_elephant"},{"featureShape":[2048],"annotation":"african_elephant"},{"annotation":"african_elephant","featureShape":[2048]},{"annotation":"african_elephant","featureShape":[2048]},{"featureShape":[2048],"annotation":"african_elephant"},{"annotation":"african_elephant","featureShape":[2048]},{"annotation":"african_elephant","featureShape":[2048]},{"featureShape":[2048],"annotation":"african_elephant"},{"annotation":"african_elephant","featureShape":[2048]},{"featureShape":[2048],"annotation":"african_elephant"},{"featureShape":[2048],"annotation":"african_elephant"},{"annotation":"african_elephant","featureShape":[2048]},{"featureShape":[2048],"annotation":"african_elephant"},{"featureShape":[2048],"annotation":"african_elephant"},{"featureShape":[2048],"annotation":"african_elephant"},{"annotation":"african_elephant","featureShape":[2048]},{"annotation":"african_elephant","featureShape":[2048]},{"featureShape":[2048],"annotation":"african_elephant"},{"featureShape":[2048],"annotation":"african_elephant"},{"featureShape":[2048],"annotation":"african_elephant"},{"annotation":"african_elephant","featureShape":[2048]},{"featureShape":[2048],"annotation":"african_elephant"},{"annotation":"african_elephant","featureShape":[2048]},{"featureShape":[2048],"annotation":"african_elephant"},{"featureShape":[2048],"annotation":"african_elephant"},{"featureShape":[2048],"annotation":"african_elephant"},{"featureShape":[2048],"annotation":"african_elephant"},{"featureShape":[2048],"annotation":"african_elephant"},{"annotation":"african_elephant","featureShape":[2048]},{"featureShape":[2048],"annotation":"african_elephant"},{"featureShape":[2048],"annotation":"african_elephant"},{"featureShape":[2048],"annotation":"african_elephant"},{"annotation":"african_elephant","featureShape":[2048]},{"annotation":"african_elephant","featureShape":[2048]},{"annotation":"african_elephant","featureShape":[2048]},{"featureShape":[2048],"annotation":"african_elephant"},{"featureShape":[2048],"annotation":"african_elephant"},{"featureShape":[2048],"annotation":"african_elephant"},{"featureShape":[2048],"annotation":"african_elephant"},{"featureShape":[2048],"annotation":"african_elephant"},{"featureShape":[2048],"annotation":"african_elephant"},{"annotation":"african_elephant","featureShape":[2048]},{"featureShape":[2048],"annotation":"african_elephant"},{"featureShape":[2048],"annotation":"african_elephant"},{"featureShape":[2048],"annotation":"african_elephant"},{"featureShape":[2048],"annotation":"african_elephant"},{"featureShape":[2048],"annotation":"african_elephant"},{"featureShape":[2048],"annotation":"african_elephant"},{"featureShape":[2048],"annotation":"african_elephant"},{"featureShape":[2048],"annotation":"african_elephant"},{"featureShape":[2048],"annotation":"african_elephant"},{"featureShape":[2048],"annotation":"african_elephant"},{"annotation":"african_elephant","featureShape":[2048]},{"featureShape":[2048],"annotation":"african_elephant"},{"featureShape":[2048],"annotation":"african_elephant"},{"annotation":"african_elephant","featureShape":[2048]},{"featureShape":[2048],"annotation":"african_elephant"},{"featureShape":[2048],"annotation":"african_elephant"},{"featureShape":[2048],"annotation":"african_elephant"},{"featureShape":[2048],"annotation":"african_elephant"},{"featureShape":[2048],"annotation":"african_elephant"},{"annotation":"african_elephant","featureShape":[2048]},{"featureShape":[2048],"annotation":"african_elephant"},{"featureShape":[2048],"annotation":"african_elephant"},{"featureShape":[2048],"annotation":"african_elephant"},{"featureShape":[2048],"annotation":"african_elephant"},{"featureShape":[2048],"annotation":"african_elephant"},{"annotation":"african_elephant","featureShape":[2048]},{"featureShape":[2048],"annotation":"african_elephant"},{"annotation":"african_elephant","featureShape":[2048]},{"featureShape":[2048],"annotation":"african_elephant"},{"annotation":"african_elephant","featureShape":[2048]},{"annotation":"african_elephant","featureShape":[2048]},{"annotation":"african_elephant","featureShape":[2048]},{"featureShape":[2048],"annotation":"african_elephant"},{"annotation":"african_elephant","featureShape":[2048]},{"featureShape":[2048],"annotation":"african_elephant"},{"annotation":"african_elephant","featureShape":[2048]},{"featureShape":[2048],"annotation":"african_elephant"},{"annotation":"african_elephant","featureShape":[2048]},{"featureShape":[2048],"annotation":"african_elephant"},{"annotation":"african_elephant","featureShape":[2048]},{"featureShape":[2048],"annotation":"african_elephant"},{"featureShape":[2048],"annotation":"african_elephant"},{"featureShape":[2048],"annotation":"african_elephant"},{"annotation":"african_elephant","featureShape":[2048]},{"annotation":"african_elephant","featureShape":[2048]},{"featureShape":[2048],"annotation":"african_elephant"},{"annotation":"african_elephant","featureShape":[2048]},{"featureShape":[2048],"annotation":"african_elephant"},{"annotation":"african_elephant","featureShape":[2048]},{"annotation":"african_elephant","featureShape":[2048]},{"featureShape":[2048],"annotation":"african_elephant"},{"annotation":"african_elephant","featureShape":[2048]},{"featureShape":[2048],"annotation":"african_elephant"},{"annotation":"african_elephant","featureShape":[2048]},{"featureShape":[2048],"annotation":"african_elephant"},{"featureShape":[2048],"annotation":"african_elephant"},{"featureShape":[2048],"annotation":"african_elephant"},{"featureShape":[2048],"annotation":"african_elephant"},{"annotation":"african_elephant","featureShape":[2048]},{"featureShape":[2048],"annotation":"african_elephant"},{"annotation":"african_elephant","featureShape":[2048]},{"featureShape":[2048],"annotation":"african_elephant"},{"featureShape":[2048],"annotation":"african_elephant"},{"featureShape":[2048],"annotation":"african_elephant"},{"featureShape":[2048],"annotation":"african_elephant"},{"annotation":"african_elephant","featureShape":[2048]},{"featureShape":[2048],"annotation":"african_elephant"},{"annotation":"african_elephant","featureShape":[2048]},{"annotation":"african_elephant","featureShape":[2048]},{"featureShape":[2048],"annotation":"african_elephant"},{"annotation":"african_elephant","featureShape":[2048]},{"annotation":"african_elephant","featureShape":[2048]},{"annotation":"african_elephant","featureShape":[2048]},{"annotation":"african_elephant","featureShape":[2048]},{"annotation":"african_elephant","featureShape":[2048]},{"featureShape":[2048],"annotation":"african_elephant"},{"featureShape":[2048],"annotation":"african_elephant"},{"featureShape":[2048],"annotation":"african_elephant"},{"featureShape":[2048],"annotation":"african_elephant"},{"featureShape":[2048],"annotation":"african_elephant"},{"annotation":"african_elephant","featureShape":[2048]},{"annotation":"african_elephant","featureShape":[2048]},{"featureShape":[2048],"annotation":"african_elephant"},{"annotation":"african_elephant","featureShape":[2048]},{"featureShape":[2048],"annotation":"african_elephant"},{"featureShape":[2048],"annotation":"african_elephant"},{"featureShape":[2048],"annotation":"african_elephant"},{"featureShape":[2048],"annotation":"african_elephant"},{"featureShape":[2048],"annotation":"african_elephant"},{"annotation":"african_elephant","featureShape":[2048]},{"featureShape":[2048],"annotation":"african_elephant"},{"annotation":"african_elephant","featureShape":[2048]},{"annotation":"african_elephant","featureShape":[2048]},{"featureShape":[2048],"annotation":"african_elephant"},{"featureShape":[2048],"annotation":"african_elephant"},{"featureShape":[2048],"annotation":"african_elephant"},{"featureShape":[2048],"annotation":"african_elephant"},{"featureShape":[2048],"annotation":"african_elephant"},{"annotation":"african_elephant","featureShape":[2048]},{"featureShape":[2048],"annotation":"african_elephant"},{"featureShape":[2048],"annotation":"african_elephant"},{"featureShape":[2048],"annotation":"african_elephant"},{"annotation":"african_elephant","featureShape":[2048]},{"featureShape":[2048],"annotation":"african_elephant"},{"annotation":"african_elephant","featureShape":[2048]},{"featureShape":[2048],"annotation":"african_elephant"},{"annotation":"african_elephant","featureShape":[2048]},{"annotation":"african_elephant","featureShape":[2048]},{"featureShape":[2048],"annotation":"african_elephant"},{"annotation":"african_elephant","featureShape":[2048]},{"featureShape":[2048],"annotation":"african_elephant"},{"featureShape":[2048],"annotation":"african_elephant"},{"annotation":"african_elephant","featureShape":[2048]},{"featureShape":[2048],"annotation":"african_elephant"},{"featureShape":[2048],"annotation":"african_elephant"},{"annotation":"african_elephant","featureShape":[2048]},{"featureShape":[2048],"annotation":"african_elephant"},{"annotation":"african_elephant","featureShape":[2048]},{"annotation":"african_elephant","featureShape":[2048]},{"featureShape":[2048],"annotation":"african_elephant"},{"annotation":"african_elephant","featureShape":[2048]},{"annotation":"african_elephant","featureShape":[2048]},{"featureShape":[2048],"annotation":"african_elephant"},{"featureShape":[2048],"annotation":"african_elephant"},{"featureShape":[2048],"annotation":"african_elephant"},{"featureShape":[2048],"annotation":"african_elephant"},{"annotation":"african_elephant","featureShape":[2048]},{"annotation":"african_elephant","featureShape":[2048]},{"featureShape":[2048],"annotation":"african_elephant"},{"featureShape":[2048],"annotation":"african_elephant"},{"featureShape":[2048],"annotation":"african_elephant"},{"featureShape":[2048],"annotation":"african_elephant"},{"annotation":"african_elephant","featureShape":[2048]},{"featureShape":[2048],"annotation":"african_elephant"},{"featureShape":[2048],"annotation":"indian_elephant"},{"featureShape":[2048],"annotation":"indian_elephant"},{"annotation":"indian_elephant","featureShape":[2048]},{"annotation":"indian_elephant","featureShape":[2048]},{"featureShape":[2048],"annotation":"indian_elephant"},{"annotation":"indian_elephant","featureShape":[2048]},{"featureShape":[2048],"annotation":"indian_elephant"},{"featureShape":[2048],"annotation":"indian_elephant"},{"annotation":"indian_elephant","featureShape":[2048]},{"featureShape":[2048],"annotation":"indian_elephant"},{"featureShape":[2048],"annotation":"indian_elephant"},{"featureShape":[2048],"annotation":"indian_elephant"},{"annotation":"indian_elephant","featureShape":[2048]},{"featureShape":[2048],"annotation":"indian_elephant"},{"featureShape":[2048],"annotation":"indian_elephant"},{"annotation":"indian_elephant","featureShape":[2048]},{"featureShape":[2048],"annotation":"indian_elephant"},{"annotation":"indian_elephant","featureShape":[2048]},{"featureShape":[2048],"annotation":"indian_elephant"},{"featureShape":[2048],"annotation":"indian_elephant"},{"featureShape":[2048],"annotation":"indian_elephant"},{"annotation":"indian_elephant","featureShape":[2048]},{"featureShape":[2048],"annotation":"indian_elephant"},{"annotation":"indian_elephant","featureShape":[2048]},{"featureShape":[2048],"annotation":"indian_elephant"},{"featureShape":[2048],"annotation":"indian_elephant"},{"featureShape":[2048],"annotation":"indian_elephant"},{"featureShape":[2048],"annotation":"indian_elephant"},{"annotation":"indian_elephant","featureShape":[2048]},{"annotation":"indian_elephant","featureShape":[2048]},{"annotation":"indian_elephant","featureShape":[2048]},{"annotation":"indian_elephant","featureShape":[2048]},{"annotation":"indian_elephant","featureShape":[2048]},{"featureShape":[2048],"annotation":"indian_elephant"},{"featureShape":[2048],"annotation":"indian_elephant"},{"featureShape":[2048],"annotation":"indian_elephant"},{"annotation":"indian_elephant","featureShape":[2048]},{"annotation":"indian_elephant","featureShape":[2048]},{"featureShape":[2048],"annotation":"indian_elephant"},{"featureShape":[2048],"annotation":"indian_elephant"},{"featureShape":[2048],"annotation":"indian_elephant"},{"featureShape":[2048],"annotation":"indian_elephant"},{"annotation":"indian_elephant","featureShape":[2048]},{"annotation":"indian_elephant","featureShape":[2048]},{"annotation":"indian_elephant","featureShape":[2048]},{"annotation":"indian_elephant","featureShape":[2048]},{"featureShape":[2048],"annotation":"indian_elephant"},{"featureShape":[2048],"annotation":"indian_elephant"},{"annotation":"indian_elephant","featureShape":[2048]},{"featureShape":[2048],"annotation":"indian_elephant"},{"featureShape":[2048],"annotation":"indian_elephant"},{"annotation":"indian_elephant","featureShape":[2048]},{"featureShape":[2048],"annotation":"indian_elephant"},{"annotation":"indian_elephant","featureShape":[2048]},{"featureShape":[2048],"annotation":"indian_elephant"},{"annotation":"indian_elephant","featureShape":[2048]},{"featureShape":[2048],"annotation":"indian_elephant"},{"annotation":"indian_elephant","featureShape":[2048]},{"annotation":"indian_elephant","featureShape":[2048]},{"annotation":"indian_elephant","featureShape":[2048]},{"featureShape":[2048],"annotation":"indian_elephant"},{"annotation":"indian_elephant","featureShape":[2048]},{"annotation":"indian_elephant","featureShape":[2048]},{"annotation":"indian_elephant","featureShape":[2048]},{"featureShape":[2048],"annotation":"indian_elephant"},{"featureShape":[2048],"annotation":"indian_elephant"},{"annotation":"indian_elephant","featureShape":[2048]},{"featureShape":[2048],"annotation":"indian_elephant"},{"featureShape":[2048],"annotation":"indian_elephant"},{"annotation":"indian_elephant","featureShape":[2048]},{"annotation":"indian_elephant","featureShape":[2048]},{"annotation":"indian_elephant","featureShape":[2048]},{"featureShape":[2048],"annotation":"indian_elephant"},{"annotation":"indian_elephant","featureShape":[2048]},{"featureShape":[2048],"annotation":"indian_elephant"},{"featureShape":[2048],"annotation":"indian_elephant"},{"featureShape":[2048],"annotation":"indian_elephant"},{"annotation":"indian_elephant","featureShape":[2048]},{"featureShape":[2048],"annotation":"indian_elephant"},{"annotation":"indian_elephant","featureShape":[2048]},{"annotation":"indian_elephant","featureShape":[2048]},{"featureShape":[2048],"annotation":"indian_elephant"},{"featureShape":[2048],"annotation":"indian_elephant"},{"featureShape":[2048],"annotation":"indian_elephant"},{"featureShape":[2048],"annotation":"indian_elephant"},{"annotation":"indian_elephant","featureShape":[2048]},{"featureShape":[2048],"annotation":"indian_elephant"},{"featureShape":[2048],"annotation":"indian_elephant"},{"annotation":"indian_elephant","featureShape":[2048]},{"annotation":"indian_elephant","featureShape":[2048]},{"featureShape":[2048],"annotation":"indian_elephant"},{"featureShape":[2048],"annotation":"indian_elephant"},{"annotation":"indian_elephant","featureShape":[2048]},{"featureShape":[2048],"annotation":"indian_elephant"},{"featureShape":[2048],"annotation":"indian_elephant"},{"featureShape":[2048],"annotation":"indian_elephant"},{"featureShape":[2048],"annotation":"indian_elephant"},{"annotation":"indian_elephant","featureShape":[2048]},{"annotation":"indian_elephant","featureShape":[2048]},{"annotation":"indian_elephant","featureShape":[2048]},{"annotation":"indian_elephant","featureShape":[2048]},{"featureShape":[2048],"annotation":"indian_elephant"},{"featureShape":[2048],"annotation":"indian_elephant"},{"annotation":"indian_elephant","featureShape":[2048]},{"featureShape":[2048],"annotation":"indian_elephant"},{"featureShape":[2048],"annotation":"indian_elephant"},{"annotation":"indian_elephant","featureShape":[2048]},{"featureShape":[2048],"annotation":"indian_elephant"},{"featureShape":[2048],"annotation":"indian_elephant"},{"annotation":"indian_elephant","featureShape":[2048]},{"featureShape":[2048],"annotation":"indian_elephant"},{"featureShape":[2048],"annotation":"indian_elephant"},{"annotation":"indian_elephant","featureShape":[2048]},{"featureShape":[2048],"annotation":"indian_elephant"},{"annotation":"indian_elephant","featureShape":[2048]},{"annotation":"indian_elephant","featureShape":[2048]},{"annotation":"indian_elephant","featureShape":[2048]},{"annotation":"indian_elephant","featureShape":[2048]},{"featureShape":[2048],"annotation":"indian_elephant"},{"featureShape":[2048],"annotation":"indian_elephant"},{"featureShape":[2048],"annotation":"indian_elephant"},{"featureShape":[2048],"annotation":"indian_elephant"},{"annotation":"indian_elephant","featureShape":[2048]},{"featureShape":[2048],"annotation":"indian_elephant"},{"featureShape":[2048],"annotation":"indian_elephant"},{"annotation":"indian_elephant","featureShape":[2048]},{"annotation":"indian_elephant","featureShape":[2048]},{"annotation":"indian_elephant","featureShape":[2048]},{"featureShape":[2048],"annotation":"indian_elephant"},{"annotation":"indian_elephant","featureShape":[2048]},{"featureShape":[2048],"annotation":"indian_elephant"},{"featureShape":[2048],"annotation":"indian_elephant"},{"annotation":"indian_elephant","featureShape":[2048]},{"annotation":"indian_elephant","featureShape":[2048]},{"featureShape":[2048],"annotation":"indian_elephant"},{"featureShape":[2048],"annotation":"indian_elephant"},{"annotation":"indian_elephant","featureShape":[2048]},{"featureShape":[2048],"annotation":"indian_elephant"},{"annotation":"indian_elephant","featureShape":[2048]},{"annotation":"indian_elephant","featureShape":[2048]},{"featureShape":[2048],"annotation":"indian_elephant"},{"annotation":"indian_elephant","featureShape":[2048]},{"annotation":"indian_elephant","featureShape":[2048]},{"annotation":"indian_elephant","featureShape":[2048]},{"featureShape":[2048],"annotation":"indian_elephant"},{"annotation":"indian_elephant","featureShape":[2048]},{"annotation":"indian_elephant","featureShape":[2048]},{"annotation":"indian_elephant","featureShape":[2048]},{"featureShape":[2048],"annotation":"indian_elephant"},{"featureShape":[2048],"annotation":"indian_elephant"},{"featureShape":[2048],"annotation":"indian_elephant"},{"annotation":"indian_elephant","featureShape":[2048]},{"featureShape":[2048],"annotation":"indian_elephant"},{"featureShape":[2048],"annotation":"indian_elephant"},{"annotation":"indian_elephant","featureShape":[2048]},{"featureShape":[2048],"annotation":"indian_elephant"},{"featureShape":[2048],"annotation":"indian_elephant"},{"featureShape":[2048],"annotation":"indian_elephant"},{"annotation":"indian_elephant","featureShape":[2048]},{"featureShape":[2048],"annotation":"indian_elephant"},{"featureShape":[2048],"annotation":"indian_elephant"},{"annotation":"indian_elephant","featureShape":[2048]},{"featureShape":[2048],"annotation":"indian_elephant"},{"featureShape":[2048],"annotation":"indian_elephant"},{"featureShape":[2048],"annotation":"indian_elephant"},{"annotation":"indian_elephant","featureShape":[2048]},{"annotation":"indian_elephant","featureShape":[2048]},{"featureShape":[2048],"annotation":"indian_elephant"},{"featureShape":[2048],"annotation":"indian_elephant"},{"annotation":"indian_elephant","featureShape":[2048]},{"annotation":"indian_elephant","featureShape":[2048]},{"featureShape":[2048],"annotation":"indian_elephant"},{"featureShape":[2048],"annotation":"indian_elephant"},{"featureShape":[2048],"annotation":"indian_elephant"},{"annotation":"indian_elephant","featureShape":[2048]},{"featureShape":[2048],"annotation":"indian_elephant"},{"annotation":"indian_elephant","featureShape":[2048]},{"annotation":"indian_elephant","featureShape":[2048]},{"featureShape":[2048],"annotation":"indian_elephant"},{"featureShape":[2048],"annotation":"indian_elephant"},{"featureShape":[2048],"annotation":"indian_elephant"},{"featureShape":[2048],"annotation":"indian_elephant"},{"featureShape":[2048],"annotation":"indian_elephant"},{"featureShape":[2048],"annotation":"indian_elephant"},{"annotation":"indian_elephant","featureShape":[2048]},{"annotation":"indian_elephant","featureShape":[2048]},{"annotation":"indian_elephant","featureShape":[2048]},{"annotation":"indian_elephant","featureShape":[2048]},{"featureShape":[2048],"annotation":"indian_elephant"},{"featureShape":[2048],"annotation":"indian_elephant"},{"annotation":"indian_elephant","featureShape":[2048]},{"featureShape":[2048],"annotation":"indian_elephant"},{"annotation":"indian_elephant","featureShape":[2048]},{"annotation":"indian_elephant","featureShape":[2048]},{"featureShape":[2048],"annotation":"indian_elephant"},{"featureShape":[2048],"annotation":"indian_elephant"},{"featureShape":[2048],"annotation":"indian_elephant"},{"annotation":"indian_elephant","featureShape":[2048]},{"annotation":"indian_elephant","featureShape":[2048]},{"featureShape":[2048],"annotation":"indian_elephant"},{"featureShape":[2048],"annotation":"indian_elephant"},{"annotation":"indian_elephant","featureShape":[2048]},{"annotation":"indian_elephant","featureShape":[2048]},{"featureShape":[2048],"annotation":"indian_elephant"},{"featureShape":[2048],"annotation":"indian_elephant"},{"annotation":"indian_elephant","featureShape":[2048]},{"featureShape":[2048],"annotation":"indian_elephant"},{"featureShape":[2048],"annotation":"indian_elephant"},{"annotation":"indian_elephant","featureShape":[2048]},{"featureShape":[2048],"annotation":"indian_elephant"},{"featureShape":[2048],"annotation":"indian_elephant"},{"featureShape":[2048],"annotation":"indian_elephant"},{"featureShape":[2048],"annotation":"indian_elephant"},{"featureShape":[2048],"annotation":"indian_elephant"},{"featureShape":[2048],"annotation":"indian_elephant"},{"annotation":"indian_elephant","featureShape":[2048]},{"annotation":"indian_elephant","featureShape":[2048]},{"featureShape":[2048],"annotation":"indian_elephant"},{"featureShape":[2048],"annotation":"indian_elephant"},{"annotation":"indian_elephant","featureShape":[2048]},{"featureShape":[2048],"annotation":"indian_elephant"},{"annotation":"indian_elephant","featureShape":[2048]},{"annotation":"indian_elephant","featureShape":[2048]},{"annotation":"indian_elephant","featureShape":[2048]},{"annotation":"indian_elephant","featureShape":[2048]},{"annotation":"indian_elephant","featureShape":[2048]},{"annotation":"indian_elephant","featureShape":[2048]},{"featureShape":[2048],"annotation":"indian_elephant"},{"featureShape":[2048],"annotation":"indian_elephant"},{"annotation":"indian_elephant","featureShape":[2048]},{"annotation":"indian_elephant","featureShape":[2048]},{"annotation":"indian_elephant","featureShape":[2048]},{"annotation":"indian_elephant","featureShape":[2048]},{"featureShape":[2048],"annotation":"indian_elephant"},{"annotation":"indian_elephant","featureShape":[2048]},{"featureShape":[2048],"annotation":"indian_elephant"},{"annotation":"indian_elephant","featureShape":[2048]},{"annotation":"indian_elephant","featureShape":[2048]},{"featureShape":[2048],"annotation":"indian_elephant"},{"featureShape":[2048],"annotation":"indian_elephant"},{"annotation":"indian_elephant","featureShape":[2048]},{"annotation":"indian_elephant","featureShape":[2048]},{"featureShape":[2048],"annotation":"indian_elephant"},{"featureShape":[2048],"annotation":"indian_elephant"},{"annotation":"indian_elephant","featureShape":[2048]},{"featureShape":[2048],"annotation":"indian_elephant"},{"featureShape":[2048],"annotation":"indian_elephant"},{"featureShape":[2048],"annotation":"indian_elephant"},{"featureShape":[2048],"annotation":"indian_elephant"},{"featureShape":[2048],"annotation":"indian_elephant"},{"featureShape":[2048],"annotation":"indian_elephant"},{"featureShape":[2048],"annotation":"indian_elephant"},{"featureShape":[2048],"annotation":"indian_elephant"},{"featureShape":[2048],"annotation":"indian_elephant"},{"featureShape":[2048],"annotation":"indian_elephant"},{"featureShape":[2048],"annotation":"indian_elephant"},{"featureShape":[2048],"annotation":"indian_elephant"},{"annotation":"indian_elephant","featureShape":[2048]},{"featureShape":[2048],"annotation":"indian_elephant"},{"annotation":"indian_elephant","featureShape":[2048]},{"annotation":"indian_elephant","featureShape":[2048]},{"featureShape":[2048],"annotation":"indian_elephant"},{"featureShape":[2048],"annotation":"indian_elephant"},{"annotation":"indian_elephant","featureShape":[2048]},{"featureShape":[2048],"annotation":"indian_elephant"},{"annotation":"indian_elephant","featureShape":[2048]},{"annotation":"indian_elephant","featureShape":[2048]},{"featureShape":[2048],"annotation":"indian_elephant"},{"annotation":"indian_elephant","featureShape":[2048]},{"annotation":"indian_elephant","featureShape":[2048]},{"featureShape":[2048],"annotation":"indian_elephant"},{"featureShape":[2048],"annotation":"indian_elephant"},{"annotation":"indian_elephant","featureShape":[2048]},{"annotation":"indian_elephant","featureShape":[2048]},{"annotation":"indian_elephant","featureShape":[2048]},{"featureShape":[2048],"annotation":"indian_elephant"},{"featureShape":[2048],"annotation":"indian_elephant"},{"featureShape":[2048],"annotation":"indian_elephant"},{"annotation":"indian_elephant","featureShape":[2048]},{"featureShape":[2048],"annotation":"indian_elephant"},{"annotation":"indian_elephant","featureShape":[2048]},{"annotation":"indian_elephant","featureShape":[2048]},{"featureShape":[2048],"annotation":"indian_elephant"},{"featureShape":[2048],"annotation":"indian_elephant"},{"annotation":"indian_elephant","featureShape":[2048]},{"annotation":"indian_elephant","featureShape":[2048]},{"annotation":"indian_elephant","featureShape":[2048]},{"featureShape":[2048],"annotation":"indian_elephant"},{"annotation":"indian_elephant","featureShape":[2048]},{"annotation":"indian_elephant","featureShape":[2048]},{"featureShape":[2048],"annotation":"indian_elephant"},{"annotation":"indian_elephant","featureShape":[2048]},{"featureShape":[2048],"annotation":"indian_elephant"},{"annotation":"indian_elephant","featureShape":[2048]},{"annotation":"indian_elephant","featureShape":[2048]},{"featureShape":[2048],"annotation":"indian_elephant"},{"annotation":"indian_elephant","featureShape":[2048]},{"featureShape":[2048],"annotation":"indian_elephant"},{"annotation":"indian_elephant","featureShape":[2048]},{"annotation":"indian_elephant","featureShape":[2048]},{"featureShape":[2048],"annotation":"indian_elephant"},{"featureShape":[2048],"annotation":"indian_elephant"},{"annotation":"indian_elephant","featureShape":[2048]},{"featureShape":[2048],"annotation":"indian_elephant"},{"annotation":"indian_elephant","featureShape":[2048]},{"annotation":"indian_elephant","featureShape":[2048]},{"featureShape":[2048],"annotation":"indian_elephant"},{"featureShape":[2048],"annotation":"indian_elephant"},{"featureShape":[2048],"annotation":"indian_elephant"},{"featureShape":[2048],"annotation":"indian_elephant"},{"annotation":"indian_elephant","featureShape":[2048]},{"featureShape":[2048],"annotation":"indian_elephant"},{"featureShape":[2048],"annotation":"indian_elephant"},{"featureShape":[2048],"annotation":"indian_elephant"},{"annotation":"indian_elephant","featureShape":[2048]},{"annotation":"indian_elephant","featureShape":[2048]},{"featureShape":[2048],"annotation":"indian_elephant"},{"featureShape":[2048],"annotation":"indian_elephant"},{"annotation":"indian_elephant","featureShape":[2048]},{"annotation":"indian_elephant","featureShape":[2048]},{"featureShape":[2048],"annotation":"indian_elephant"},{"annotation":"indian_elephant","featureShape":[2048]},{"annotation":"indian_elephant","featureShape":[2048]},{"featureShape":[2048],"annotation":"indian_elephant"},{"featureShape":[2048],"annotation":"indian_elephant"},{"featureShape":[2048],"annotation":"indian_elephant"},{"featureShape":[2048],"annotation":"indian_elephant"},{"annotation":"indian_elephant","featureShape":[2048]},{"annotation":"indian_elephant","featureShape":[2048]},{"featureShape":[2048],"annotation":"indian_elephant"},{"annotation":"indian_elephant","featureShape":[2048]},{"featureShape":[2048],"annotation":"indian_elephant"},{"featureShape":[2048],"annotation":"indian_elephant"},{"annotation":"indian_elephant","featureShape":[2048]},{"featureShape":[2048],"annotation":"indian_elephant"},{"annotation":"indian_elephant","featureShape":[2048]},{"annotation":"indian_elephant","featureShape":[2048]},{"annotation":"indian_elephant","featureShape":[2048]},{"annotation":"indian_elephant","featureShape":[2048]},{"annotation":"indian_elephant","featureShape":[2048]},{"featureShape":[2048],"annotation":"indian_elephant"},{"featureShape":[2048],"annotation":"indian_elephant"},{"featureShape":[2048],"annotation":"indian_elephant"},{"annotation":"indian_elephant","featureShape":[2048]},{"featureShape":[2048],"annotation":"indian_elephant"},{"annotation":"indian_elephant","featureShape":[2048]},{"featureShape":[2048],"annotation":"indian_elephant"},{"annotation":"indian_elephant","featureShape":[2048]},{"featureShape":[2048],"annotation":"indian_elephant"},{"featureShape":[2048],"annotation":"indian_elephant"},{"featureShape":[2048],"annotation":"indian_elephant"},{"annotation":"indian_elephant","featureShape":[2048]},{"annotation":"indian_elephant","featureShape":[2048]},{"annotation":"indian_elephant","featureShape":[2048]},{"annotation":"indian_elephant","featureShape":[2048]},{"annotation":"indian_elephant","featureShape":[2048]},{"annotation":"indian_elephant","featureShape":[2048]},{"featureShape":[2048],"annotation":"indian_elephant"},{"featureShape":[2048],"annotation":"indian_elephant"},{"annotation":"indian_elephant","featureShape":[2048]},{"annotation":"indian_elephant","featureShape":[2048]},{"featureShape":[2048],"annotation":"indian_elephant"},{"annotation":"indian_elephant","featureShape":[2048]},{"annotation":"indian_elephant","featureShape":[2048]},{"annotation":"indian_elephant","featureShape":[2048]},{"featureShape":[2048],"annotation":"indian_elephant"},{"featureShape":[2048],"annotation":"indian_elephant"},{"featureShape":[2048],"annotation":"indian_elephant"},{"featureShape":[2048],"annotation":"indian_elephant"},{"featureShape":[2048],"annotation":"indian_elephant"},{"annotation":"indian_elephant","featureShape":[2048]},{"annotation":"indian_elephant","featureShape":[2048]},{"annotation":"indian_elephant","featureShape":[2048]},{"featureShape":[2048],"annotation":"indian_elephant"},{"annotation":"indian_elephant","featureShape":[2048]},{"annotation":"indian_elephant","featureShape":[2048]},{"annotation":"indian_elephant","featureShape":[2048]},{"featureShape":[2048],"annotation":"indian_elephant"},{"featureShape":[2048],"annotation":"indian_elephant"},{"featureShape":[2048],"annotation":"indian_elephant"},{"featureShape":[2048],"annotation":"indian_elephant"},{"featureShape":[2048],"annotation":"indian_elephant"},{"annotation":"indian_elephant","featureShape":[2048]},{"featureShape":[2048],"annotation":"indian_elephant"},{"featureShape":[2048],"annotation":"indian_elephant"},{"annotation":"indian_elephant","featureShape":[2048]},{"annotation":"indian_elephant","featureShape":[2048]},{"featureShape":[2048],"annotation":"indian_elephant"},{"featureShape":[2048],"annotation":"indian_elephant"},{"featureShape":[2048],"annotation":"indian_elephant"},{"featureShape":[2048],"annotation":"indian_elephant"},{"featureShape":[2048],"annotation":"indian_elephant"},{"featureShape":[2048],"annotation":"indian_elephant"},{"annotation":"indian_elephant","featureShape":[2048]},{"annotation":"indian_elephant","featureShape":[2048]},{"featureShape":[2048],"annotation":"indian_elephant"},{"featureShape":[2048],"annotation":"indian_elephant"},{"featureShape":[2048],"annotation":"indian_elephant"},{"featureShape":[2048],"annotation":"indian_elephant"},{"featureShape":[2048],"annotation":"indian_elephant"},{"featureShape":[2048],"annotation":"indian_elephant"},{"annotation":"indian_elephant","featureShape":[2048]},{"featureShape":[2048],"annotation":"indian_elephant"},{"featureShape":[2048],"annotation":"indian_elephant"},{"annotation":"indian_elephant","featureShape":[2048]},{"annotation":"indian_elephant","featureShape":[2048]},{"featureShape":[2048],"annotation":"indian_elephant"},{"featureShape":[2048],"annotation":"indian_elephant"},{"featureShape":[2048],"annotation":"indian_elephant"},{"featureShape":[2048],"annotation":"indian_elephant"},{"annotation":"indian_elephant","featureShape":[2048]},{"annotation":"indian_elephant","featureShape":[2048]},{"featureShape":[2048],"annotation":"indian_elephant"},{"featureShape":[2048],"annotation":"indian_elephant"},{"annotation":"indian_elephant","featureShape":[2048]},{"featureShape":[2048],"annotation":"indian_elephant"},{"annotation":"indian_elephant","featureShape":[2048]},{"featureShape":[2048],"annotation":"indian_elephant"},{"annotation":"indian_elephant","featureShape":[2048]},{"annotation":"indian_elephant","featureShape":[2048]},{"featureShape":[2048],"annotation":"indian_elephant"},{"featureShape":[2048],"annotation":"indian_elephant"},{"featureShape":[2048],"annotation":"indian_elephant"},{"featureShape":[2048],"annotation":"indian_elephant"},{"featureShape":[2048],"annotation":"indian_elephant"},{"featureShape":[2048],"annotation":"indian_elephant"},{"featureShape":[2048],"annotation":"indian_elephant"},{"annotation":"indian_elephant","featureShape":[2048]},{"featureShape":[2048],"annotation":"indian_elephant"},{"annotation":"indian_elephant","featureShape":[2048]},{"annotation":"indian_elephant","featureShape":[2048]},{"annotation":"indian_elephant","featureShape":[2048]},{"annotation":"indian_elephant","featureShape":[2048]},{"featureShape":[2048],"annotation":"indian_elephant"},{"featureShape":[2048],"annotation":"indian_elephant"},{"featureShape":[2048],"annotation":"indian_elephant"},{"annotation":"indian_elephant","featureShape":[2048]},{"featureShape":[2048],"annotation":"indian_elephant"},{"featureShape":[2048],"annotation":"indian_elephant"},{"featureShape":[2048],"annotation":"indian_elephant"},{"featureShape":[2048],"annotation":"indian_elephant"},{"annotation":"indian_elephant","featureShape":[2048]},{"annotation":"indian_elephant","featureShape":[2048]},{"annotation":"indian_elephant","featureShape":[2048]},{"annotation":"indian_elephant","featureShape":[2048]},{"featureShape":[2048],"annotation":"indian_elephant"},{"annotation":"indian_elephant","featureShape":[2048]},{"featureShape":[2048],"annotation":"indian_elephant"},{"featureShape":[2048],"annotation":"indian_elephant"},{"featureShape":[2048],"annotation":"indian_elephant"},{"featureShape":[2048],"annotation":"indian_elephant"},{"featureShape":[2048],"annotation":"indian_elephant"},{"annotation":"indian_elephant","featureShape":[2048]},{"annotation":"indian_elephant","featureShape":[2048]},{"featureShape":[2048],"annotation":"indian_elephant"},{"annotation":"indian_elephant","featureShape":[2048]},{"featureShape":[2048],"annotation":"indian_elephant"},{"featureShape":[2048],"annotation":"indian_elephant"},{"annotation":"indian_elephant","featureShape":[2048]},{"featureShape":[2048],"annotation":"indian_elephant"},{"featureShape":[2048],"annotation":"indian_elephant"},{"annotation":"indian_elephant","featureShape":[2048]},{"annotation":"indian_elephant","featureShape":[2048]},{"featureShape":[2048],"annotation":"indian_elephant"},{"featureShape":[2048],"annotation":"indian_elephant"},{"featureShape":[2048],"annotation":"indian_elephant"},{"annotation":"indian_elephant","featureShape":[2048]},{"annotation":"indian_elephant","featureShape":[2048]},{"featureShape":[2048],"annotation":"indian_elephant"},{"annotation":"indian_elephant","featureShape":[2048]},{"featureShape":[2048],"annotation":"indian_elephant"},{"annotation":"indian_elephant","featureShape":[2048]},{"featureShape":[2048],"annotation":"indian_elephant"},{"annotation":"indian_elephant","featureShape":[2048]},{"featureShape":[2048],"annotation":"indian_elephant"},{"featureShape":[2048],"annotation":"indian_elephant"},{"annotation":"indian_elephant","featureShape":[2048]},{"annotation":"indian_elephant","featureShape":[2048]},{"annotation":"indian_elephant","featureShape":[2048]},{"annotation":"indian_elephant","featureShape":[2048]},{"featureShape":[2048],"annotation":"indian_elephant"},{"annotation":"indian_elephant","featureShape":[2048]},{"annotation":"indian_elephant","featureShape":[2048]},{"featureShape":[2048],"annotation":"indian_elephant"},{"featureShape":[2048],"annotation":"indian_elephant"},{"featureShape":[2048],"annotation":"indian_elephant"},{"featureShape":[2048],"annotation":"indian_elephant"},{"annotation":"indian_elephant","featureShape":[2048]},{"featureShape":[2048],"annotation":"indian_elephant"},{"featureShape":[2048],"annotation":"indian_elephant"},{"annotation":"indian_elephant","featureShape":[2048]},{"annotation":"indian_elephant","featureShape":[2048]},{"annotation":"indian_elephant","featureShape":[2048]},{"featureShape":[2048],"annotation":"indian_elephant"},{"featureShape":[2048],"annotation":"indian_elephant"},{"featureShape":[2048],"annotation":"indian_elephant"},{"annotation":"indian_elephant","featureShape":[2048]},{"annotation":"indian_elephant","featureShape":[2048]},{"featureShape":[2048],"annotation":"indian_elephant"},{"featureShape":[2048],"annotation":"indian_elephant"},{"annotation":"indian_elephant","featureShape":[2048]},{"annotation":"indian_elephant","featureShape":[2048]},{"featureShape":[2048],"annotation":"indian_elephant"},{"featureShape":[2048],"annotation":"indian_elephant"},{"annotation":"indian_elephant","featureShape":[2048]},{"annotation":"indian_elephant","featureShape":[2048]},{"featureShape":[2048],"annotation":"indian_elephant"},{"annotation":"indian_elephant","featureShape":[2048]},{"featureShape":[2048],"annotation":"indian_elephant"},{"featureShape":[2048],"annotation":"indian_elephant"},{"featureShape":[2048],"annotation":"indian_elephant"},{"featureShape":[2048],"annotation":"indian_elephant"},{"annotation":"indian_elephant","featureShape":[2048]},{"annotation":"indian_elephant","featureShape":[2048]},{"annotation":"indian_elephant","featureShape":[2048]},{"annotation":"indian_elephant","featureShape":[2048]},{"featureShape":[2048],"annotation":"indian_elephant"},{"featureShape":[2048],"annotation":"indian_elephant"},{"featureShape":[2048],"annotation":"indian_elephant"},{"annotation":"indian_elephant","featureShape":[2048]},{"featureShape":[2048],"annotation":"indian_elephant"},{"featureShape":[2048],"annotation":"indian_elephant"},{"annotation":"indian_elephant","featureShape":[2048]},{"featureShape":[2048],"annotation":"indian_elephant"},{"featureShape":[2048],"annotation":"indian_elephant"},{"annotation":"indian_elephant","featureShape":[2048]},{"featureShape":[2048],"annotation":"indian_elephant"},{"annotation":"indian_elephant","featureShape":[2048]},{"featureShape":[2048],"annotation":"indian_elephant"},{"featureShape":[2048],"annotation":"indian_elephant"},{"featureShape":[2048],"annotation":"indian_elephant"},{"annotation":"indian_elephant","featureShape":[2048]},{"featureShape":[2048],"annotation":"indian_elephant"},{"annotation":"indian_elephant","featureShape":[2048]},{"featureShape":[2048],"annotation":"indian_elephant"},{"featureShape":[2048],"annotation":"indian_elephant"},{"annotation":"indian_elephant","featureShape":[2048]},{"featureShape":[2048],"annotation":"indian_elephant"},{"featureShape":[2048],"annotation":"indian_elephant"},{"featureShape":[2048],"annotation":"indian_elephant"},{"annotation":"indian_elephant","featureShape":[2048]},{"featureShape":[2048],"annotation":"indian_elephant"},{"featureShape":[2048],"annotation":"indian_elephant"},{"featureShape":[2048],"annotation":"indian_elephant"},{"annotation":"indian_elephant","featureShape":[2048]},{"featureShape":[2048],"annotation":"indian_elephant"},{"annotation":"indian_elephant","featureShape":[2048]},{"annotation":"indian_elephant","featureShape":[2048]},{"featureShape":[2048],"annotation":"indian_elephant"},{"annotation":"indian_elephant","featureShape":[2048]},{"annotation":"indian_elephant","featureShape":[2048]},{"annotation":"indian_elephant","featureShape":[2048]},{"featureShape":[2048],"annotation":"indian_elephant"},{"featureShape":[2048],"annotation":"indian_elephant"},{"featureShape":[2048],"annotation":"indian_elephant"},{"annotation":"indian_elephant","featureShape":[2048]},{"annotation":"indian_elephant","featureShape":[2048]},{"annotation":"indian_elephant","featureShape":[2048]},{"annotation":"indian_elephant","featureShape":[2048]},{"annotation":"indian_elephant","featureShape":[2048]},{"annotation":"indian_elephant","featureShape":[2048]},{"featureShape":[2048],"annotation":"indian_elephant"},{"annotation":"indian_elephant","featureShape":[2048]},{"featureShape":[2048],"annotation":"indian_elephant"},{"annotation":"indian_elephant","featureShape":[2048]},{"annotation":"indian_elephant","featureShape":[2048]},{"annotation":"indian_elephant","featureShape":[2048]},{"annotation":"indian_elephant","featureShape":[2048]},{"annotation":"indian_elephant","featureShape":[2048]},{"featureShape":[2048],"annotation":"indian_elephant"},{"annotation":"indian_elephant","featureShape":[2048]},{"annotation":"indian_elephant","featureShape":[2048]},{"featureShape":[2048],"annotation":"indian_elephant"},{"featureShape":[2048],"annotation":"indian_elephant"},{"annotation":"indian_elephant","featureShape":[2048]},{"featureShape":[2048],"annotation":"indian_elephant"},{"featureShape":[2048],"annotation":"indian_elephant"},{"featureShape":[2048],"annotation":"indian_elephant"},{"featureShape":[2048],"annotation":"indian_elephant"},{"annotation":"indian_elephant","featureShape":[2048]},{"annotation":"indian_elephant","featureShape":[2048]},{"featureShape":[2048],"annotation":"indian_elephant"},{"annotation":"indian_elephant","featureShape":[2048]},{"featureShape":[2048],"annotation":"indian_elephant"},{"annotation":"indian_elephant","featureShape":[2048]},{"annotation":"indian_elephant","featureShape":[2048]},{"annotation":"indian_elephant","featureShape":[2048]},{"annotation":"indian_elephant","featureShape":[2048]},{"featureShape":[2048],"annotation":"indian_elephant"},{"featureShape":[2048],"annotation":"indian_elephant"},{"annotation":"indian_elephant","featureShape":[2048]},{"featureShape":[2048],"annotation":"indian_elephant"},{"annotation":"indian_elephant","featureShape":[2048]},{"annotation":"indian_elephant","featureShape":[2048]},{"annotation":"indian_elephant","featureShape":[2048]},{"annotation":"indian_elephant","featureShape":[2048]},{"annotation":"indian_elephant","featureShape":[2048]},{"featureShape":[2048],"annotation":"indian_elephant"},{"featureShape":[2048],"annotation":"indian_elephant"},{"featureShape":[2048],"annotation":"indian_elephant"},{"annotation":"indian_elephant","featureShape":[2048]},{"annotation":"indian_elephant","featureShape":[2048]},{"annotation":"indian_elephant","featureShape":[2048]},{"featureShape":[2048],"annotation":"indian_elephant"},{"annotation":"indian_elephant","featureShape":[2048]},{"annotation":"indian_elephant","featureShape":[2048]},{"annotation":"indian_elephant","featureShape":[2048]},{"featureShape":[2048],"annotation":"indian_elephant"},{"featureShape":[2048],"annotation":"indian_elephant"},{"annotation":"indian_elephant","featureShape":[2048]},{"annotation":"indian_elephant","featureShape":[2048]},{"annotation":"indian_elephant","featureShape":[2048]},{"annotation":"indian_elephant","featureShape":[2048]},{"annotation":"indian_elephant","featureShape":[2048]},{"featureShape":[2048],"annotation":"indian_elephant"},{"annotation":"indian_elephant","featureShape":[2048]},{"featureShape":[2048],"annotation":"indian_elephant"},{"featureShape":[2048],"annotation":"indian_elephant"},{"featureShape":[2048],"annotation":"indian_elephant"},{"featureShape":[2048],"annotation":"indian_elephant"},{"featureShape":[2048],"annotation":"indian_elephant"},{"annotation":"indian_elephant","featureShape":[2048]},{"featureShape":[2048],"annotation":"indian_elephant"},{"featureShape":[2048],"annotation":"indian_elephant"},{"featureShape":[2048],"annotation":"indian_elephant"},{"featureShape":[2048],"annotation":"indian_elephant"},{"featureShape":[2048],"annotation":"indian_elephant"},{"featureShape":[2048],"annotation":"indian_elephant"},{"annotation":"indian_elephant","featureShape":[2048]},{"annotation":"indian_elephant","featureShape":[2048]},{"annotation":"indian_elephant","featureShape":[2048]},{"featureShape":[2048],"annotation":"indian_elephant"},{"annotation":"indian_elephant","featureShape":[2048]},{"annotation":"indian_elephant","featureShape":[2048]},{"featureShape":[2048],"annotation":"indian_elephant"},{"annotation":"indian_elephant","featureShape":[2048]},{"annotation":"indian_elephant","featureShape":[2048]},{"featureShape":[2048],"annotation":"indian_elephant"},{"featureShape":[2048],"annotation":"indian_elephant"},{"annotation":"indian_elephant","featureShape":[2048]},{"annotation":"indian_elephant","featureShape":[2048]},{"annotation":"indian_elephant","featureShape":[2048]},{"featureShape":[2048],"annotation":"indian_elephant"},{"featureShape":[2048],"annotation":"indian_elephant"},{"featureShape":[2048],"annotation":"indian_elephant"},{"annotation":"indian_elephant","featureShape":[2048]},{"featureShape":[2048],"annotation":"indian_elephant"},{"annotation":"indian_elephant","featureShape":[2048]},{"annotation":"indian_elephant","featureShape":[2048]},{"annotation":"indian_elephant","featureShape":[2048]},{"annotation":"indian_elephant","featureShape":[2048]},{"annotation":"indian_elephant","featureShape":[2048]},{"featureShape":[2048],"annotation":"indian_elephant"},{"featureShape":[2048],"annotation":"indian_elephant"},{"annotation":"indian_elephant","featureShape":[2048]},{"featureShape":[2048],"annotation":"indian_elephant"},{"featureShape":[2048],"annotation":"indian_elephant"},{"annotation":"indian_elephant","featureShape":[2048]},{"annotation":"indian_elephant","featureShape":[2048]},{"annotation":"indian_elephant","featureShape":[2048]},{"featureShape":[2048],"annotation":"indian_elephant"},{"featureShape":[2048],"annotation":"indian_elephant"},{"annotation":"indian_elephant","featureShape":[2048]},{"annotation":"indian_elephant","featureShape":[2048]},{"featureShape":[2048],"annotation":"indian_elephant"},{"annotation":"indian_elephant","featureShape":[2048]},{"annotation":"indian_elephant","featureShape":[2048]},{"featureShape":[2048],"annotation":"indian_elephant"},{"annotation":"indian_elephant","featureShape":[2048]},{"annotation":"indian_elephant","featureShape":[2048]},{"featureShape":[2048],"annotation":"indian_elephant"},{"featureShape":[2048],"annotation":"indian_elephant"},{"featureShape":[2048],"annotation":"indian_elephant"},{"annotation":"indian_elephant","featureShape":[2048]},{"annotation":"indian_elephant","featureShape":[2048]},{"annotation":"indian_elephant","featureShape":[2048]},{"featureShape":[2048],"annotation":"indian_elephant"},{"featureShape":[2048],"annotation":"indian_elephant"},{"featureShape":[2048],"annotation":"indian_elephant"},{"featureShape":[2048],"annotation":"indian_elephant"},{"annotation":"indian_elephant","featureShape":[2048]},{"annotation":"indian_elephant","featureShape":[2048]},{"annotation":"indian_elephant","featureShape":[2048]},{"featureShape":[2048],"annotation":"indian_elephant"},{"featureShape":[2048],"annotation":"indian_elephant"},{"annotation":"indian_elephant","featureShape":[2048]},{"featureShape":[2048],"annotation":"indian_elephant"},{"annotation":"indian_elephant","featureShape":[2048]},{"featureShape":[2048],"annotation":"indian_elephant"},{"annotation":"indian_elephant","featureShape":[2048]},{"featureShape":[2048],"annotation":"indian_elephant"},{"annotation":"indian_elephant","featureShape":[2048]},{"featureShape":[2048],"annotation":"indian_elephant"},{"featureShape":[2048],"annotation":"indian_elephant"},{"featureShape":[2048],"annotation":"indian_elephant"},{"featureShape":[2048],"annotation":"indian_elephant"},{"featureShape":[2048],"annotation":"indian_elephant"},{"annotation":"indian_elephant","featureShape":[2048]},{"featureShape":[2048],"annotation":"indian_elephant"},{"annotation":"indian_elephant","featureShape":[2048]},{"annotation":"indian_elephant","featureShape":[2048]},{"featureShape":[2048],"annotation":"indian_elephant"},{"featureShape":[2048],"annotation":"indian_elephant"},{"featureShape":[2048],"annotation":"indian_elephant"},{"featureShape":[2048],"annotation":"indian_elephant"},{"annotation":"indian_elephant","featureShape":[2048]},{"annotation":"indian_elephant","featureShape":[2048]},{"annotation":"indian_elephant","featureShape":[2048]},{"featureShape":[2048],"annotation":"indian_elephant"},{"featureShape":[2048],"annotation":"indian_elephant"},{"featureShape":[2048],"annotation":"indian_elephant"},{"featureShape":[2048],"annotation":"indian_elephant"},{"featureShape":[2048],"annotation":"indian_elephant"},{"featureShape":[2048],"annotation":"indian_elephant"},{"featureShape":[2048],"annotation":"indian_elephant"},{"annotation":"indian_elephant","featureShape":[2048]},{"annotation":"indian_elephant","featureShape":[2048]},{"featureShape":[2048],"annotation":"indian_elephant"},{"featureShape":[2048],"annotation":"indian_elephant"},{"featureShape":[2048],"annotation":"indian_elephant"},{"annotation":"indian_elephant","featureShape":[2048]},{"annotation":"indian_elephant","featureShape":[2048]},{"annotation":"indian_elephant","featureShape":[2048]},{"featureShape":[2048],"annotation":"indian_elephant"},{"annotation":"indian_elephant","featureShape":[2048]},{"annotation":"indian_elephant","featureShape":[2048]},{"featureShape":[2048],"annotation":"indian_elephant"},{"annotation":"indian_elephant","featureShape":[2048]},{"featureShape":[2048],"annotation":"indian_elephant"},{"annotation":"indian_elephant","featureShape":[2048]},{"annotation":"indian_elephant","featureShape":[2048]},{"annotation":"indian_elephant","featureShape":[2048]},{"annotation":"indian_elephant","featureShape":[2048]},{"featureShape":[2048],"annotation":"indian_elephant"},{"featureShape":[2048],"annotation":"indian_elephant"},{"annotation":"indian_elephant","featureShape":[2048]},{"annotation":"indian_elephant","featureShape":[2048]},{"annotation":"indian_elephant","featureShape":[2048]},{"annotation":"indian_elephant","featureShape":[2048]},{"annotation":"indian_elephant","featureShape":[2048]},{"featureShape":[2048],"annotation":"indian_elephant"},{"annotation":"indian_elephant","featureShape":[2048]},{"annotation":"indian_elephant","featureShape":[2048]},{"annotation":"indian_elephant","featureShape":[2048]},{"featureShape":[2048],"annotation":"indian_elephant"},{"annotation":"indian_elephant","featureShape":[2048]},{"annotation":"indian_elephant","featureShape":[2048]},{"annotation":"indian_elephant","featureShape":[2048]},{"annotation":"indian_elephant","featureShape":[2048]},{"annotation":"indian_elephant","featureShape":[2048]},{"featureShape":[2048],"annotation":"indian_elephant"},{"featureShape":[2048],"annotation":"indian_elephant"},{"featureShape":[2048],"annotation":"indian_elephant"},{"featureShape":[2048],"annotation":"indian_elephant"},{"featureShape":[2048],"annotation":"indian_elephant"},{"annotation":"indian_elephant","featureShape":[2048]},{"featureShape":[2048],"annotation":"indian_elephant"},{"featureShape":[2048],"annotation":"indian_elephant"},{"featureShape":[2048],"annotation":"indian_elephant"},{"annotation":"indian_elephant","featureShape":[2048]},{"annotation":"indian_elephant","featureShape":[2048]},{"annotation":"indian_elephant","featureShape":[2048]},{"featureShape":[2048],"annotation":"indian_elephant"},{"featureShape":[2048],"annotation":"indian_elephant"},{"annotation":"indian_elephant","featureShape":[2048]},{"annotation":"indian_elephant","featureShape":[2048]},{"featureShape":[2048],"annotation":"indian_elephant"},{"featureShape":[2048],"annotation":"indian_elephant"},{"annotation":"indian_elephant","featureShape":[2048]},{"annotation":"indian_elephant","featureShape":[2048]},{"featureShape":[2048],"annotation":"indian_elephant"},{"annotation":"indian_elephant","featureShape":[2048]},{"featureShape":[2048],"annotation":"indian_elephant"},{"annotation":"indian_elephant","featureShape":[2048]},{"featureShape":[2048],"annotation":"indian_elephant"},{"annotation":"indian_elephant","featureShape":[2048]},{"featureShape":[2048],"annotation":"indian_elephant"},{"featureShape":[2048],"annotation":"indian_elephant"},{"featureShape":[2048],"annotation":"indian_elephant"},{"annotation":"indian_elephant","featureShape":[2048]},{"featureShape":[2048],"annotation":"indian_elephant"},{"featureShape":[2048],"annotation":"indian_elephant"},{"featureShape":[2048],"annotation":"indian_elephant"},{"featureShape":[2048],"annotation":"indian_elephant"},{"annotation":"indian_elephant","featureShape":[2048]},{"annotation":"indian_elephant","featureShape":[2048]},{"featureShape":[2048],"annotation":"indian_elephant"},{"annotation":"indian_elephant","featureShape":[2048]},{"annotation":"indian_elephant","featureShape":[2048]},{"annotation":"indian_elephant","featureShape":[2048]},{"annotation":"indian_elephant","featureShape":[2048]}]